bindings/__init__.py
bindings/binding.py
bindings/bindings.py
bindings/secret.py
service_bindings-1.0.0.dist-info/LICENSE
service_bindings-1.0.0.dist-info/WHEEL
service_bindings-1.0.0.dist-info/METADATA
service_bindings-1.0.0.dist-info/RECORD
