Metadata-Version: 2.1
Name: service-bindings
Version: 1.0.0
Summary: A library to access [Service Binding Specification for Kubernetes](https://k8s-service-bindings.github.io/spec/) conformant Service Binding [Workload Projections](https://k8s-service-bindings.github.io/spec/#workload-projection).
Home-page: https://github.com/nebhale/client-python
License: Apache-2.0
Author: Ben Hale
Author-email: nebhale@nebhale.com
Requires-Python: >=3.9,<4.0
Classifier: Development Status :: 5 - Production/Stable
Classifier: Intended Audience :: Developers
Classifier: License :: OSI Approved :: Apache Software License
Classifier: Programming Language :: Python :: 3
Classifier: Programming Language :: Python :: 3 :: Only
Classifier: Programming Language :: Python :: 3.9
Classifier: Topic :: Software Development :: Libraries :: Application Frameworks
Project-URL: Repository, https://github.com/nebhale/client-python
